{
  "jobId": "mysql-glucose-sync",
  "lastRunAtMs": 1775564400970,
  "lastFinishAtMs": 1775564403148,
  "lastDurationMs": 2178,
  "exitCode": 0,
  "lastStatus": "warn",
  "consecutiveErrors": 11,
  "signal": null,
  "spawnError": null,
  "outcome": {
    "status": "partial",
    "summary": "1 query error(s) — fetched 600, inserted 6",
    "metrics": {
      "batches": 6,
      "totalFetched": 600,
      "rowsInserted": 6,
      "rowsBefore": 12092,
      "rowsAfter": 12098,
      "safetyLimitHit": false,
      "ageCutoffReached": true,
      "queryErrors": 1,
      "dashboardUpdated": false
    }
  }
}